<!DOCTYPE node PUBLIC "-//freedesktop//DTD D-BUS Object Introspection 1.0//EN" "http://www.freedesktop.org/standards/dbus/1.0/introspect.dtd">
<node>
  <interface name="org.gnome.LightDisplayManager.Display">
    <method name="StartAuthentication">
      <annotation name="org.freedesktop.DBus.GLib.Async" value="true"/>
      <arg name="username" direction="in" type="s"/>
      <arg name="requests" direction="out" type="ia(is)"/>
    </method>
    <method name="ContinueAuthentication">
      <annotation name="org.freedesktop.DBus.GLib.Async" value="true"/>
      <arg name="secrets" direction="in" type="as"/>
      <arg name="requests" direction="out" type="ia(is)"/>
    </method>
  </interface>
</node>
